auto_ml_openai_sdk/__init__.py
auto_ml_openai_sdk/pipeline/__init__.py
auto_ml_openai_sdk/pipeline/clients/__init__.py
auto_ml_openai_sdk/pipeline/clients/callback_client.py
auto_ml_openai_sdk/pipeline/components/__init__.py
auto_ml_openai_sdk/pipeline/components/helper.py
auto_ml_openai_sdk/pipeline/components/operation_func.py
auto_ml_openai_sdk/pipeline/components/kubeflow/__init__.py
auto_ml_openai_sdk/pipeline/components/kubeflow/operations.py
auto_ml_openai_sdk/pipeline/config/__init__.py
auto_ml_openai_sdk/pipeline/config/config.py
auto_ml_openai_sdk/pipeline/config/settings.toml
auto_ml_openai_sdk/pipeline/openaigpt3/__init__.py
auto_ml_openai_sdk/pipeline/openaigpt3/openaigpt3.py
auto_ml_openai_sdk/pipeline/preprocessor/__init__.py
auto_ml_openai_sdk/pipeline/preprocessor/base_preprocessor.py
auto_ml_openai_sdk/pipeline/preprocessor/openai_gpt3_preprocessor.py
auto_ml_openai_sdk/pipeline/preprocessor/preprocess_utils.py
auto_ml_openai_sdk/pipeline/preprocessor/preprocessor_factory.py
auto_ml_openai_sdk/pipeline/retriever/__init__.py
auto_ml_openai_sdk/pipeline/retriever/base_retriever.py
auto_ml_openai_sdk/pipeline/retriever/cloud_retriever.py
auto_ml_openai_sdk/pipeline/retriever/retriever_factory.py
auto_ml_openai_sdk/pipeline/retriever/s3_retriever.py
auto_ml_openai_sdk/pipeline/utils/__init__.py
auto_ml_openai_sdk/pipeline/utils/data_classes.py
auto_ml_openai_sdk/pipeline/utils/exceptions.py
auto_ml_openai_sdk/pipeline/utils/formatter.py
auto_ml_openai_sdk/pipeline/utils/log.py
auto_ml_openai_sdk/pipeline/utils/openai_tools.py
auto_ml_openai_sdk/pipeline/utils/removal_helpers.py
auto_ml_openai_sdk/pipeline/utils/s3_tools.py
auto_ml_openai_sdk/pipeline/utils/versions.py
auto_ml_openai_sdk/pipeline/utils/zip_helpers.py
test/__init__.py
test/conftest.py
test/auto_ml_openai_sdk/__init__.py
test/auto_ml_openai_sdk/pipeline/__init__.py
test/auto_ml_openai_sdk/pipeline/test_data_preparation_operation_func.py
auto_ml_openai_sdk-0.0.30.dist-info/METADATA
auto_ml_openai_sdk-0.0.30.dist-info/WHEEL
auto_ml_openai_sdk-0.0.30.dist-info/top_level.txt
auto_ml_openai_sdk-0.0.30.dist-info/RECORD
