Metadata-Version: 2.1
Name: auto-ml-openai-sdk
Version: 0.0.30
Summary: Async requests
Home-page: https://github.expedia.biz/AI/auto-ml-openai-sdk
Author: alchowdhury
Author-email: alchowdhury@expediagroup.com
License: UNKNOWN
Platform: UNKNOWN
Requires-Python: >=3.6
Requires-Dist: twine (>=3.7.1)
Requires-Dist: pandas (>=1.1.5)
Requires-Dist: kfp (==1.3.0)
Requires-Dist: boto3 (==1.17.49)
Requires-Dist: wget (>=3.2)
Requires-Dist: dynaconf (>=3.1.5)
Requires-Dist: openai (>=0.8.0)
Requires-Dist: nltk (>=3.6.7)
Requires-Dist: dataclasses-json
Requires-Dist: requests
Requires-Dist: types-requests
